{
    "title": "Credentials information",
    "type": "object",
    "properties": {
        "admin-user": {
            "description": "OS admin username - required for create",
            "type": "string"
        },
        "admin-password": {
            "description": "OS admin password - required for create",
            "type": "string"
        },
        "zvm-logonby": {
            "description": "Logonby user to log on z/VM - use null to unset",
            "type": [
                "string",
                "null"
            ]
        },
        "zvm-password": {
            "description": "Password to log on z/VM - required for zVM guests",
            "type": "string"
        }
    },
    "additionalProperties": false
}
